setup.py
chromescript/__init__.py
chromescript.egg-info/PKG-INFO
chromescript.egg-info/SOURCES.txt
chromescript.egg-info/dependency_links.txt
chromescript.egg-info/not-zip-safe
chromescript.egg-info/requires.txt
chromescript.egg-info/top_level.txt