Metadata-Version: 1.0
Name: chromescript
Version: 0.1
Summary: Control Google Chrome via Applescript.
Home-page: http://github.com/deactivated/chromescript
Author: Mike Spindel
Author-email: mike@spindel.is
License: MIT
Keywords: google chrome applescript
Platform: UNKNOWN
Classifier: Development Status :: 4 - Beta
Classifier: License :: OSI Approved :: MIT License
Classifier: Intended Audience :: Developers
Classifier: Natural Language :: English
Classifier: Programming Language :: Python
